btester/__init__.py
btester/btester.py
btester-0.1.1.dist-info/LICENSE
btester-0.1.1.dist-info/METADATA
btester-0.1.1.dist-info/WHEEL
btester-0.1.1.dist-info/top_level.txt
btester-0.1.1.dist-info/RECORD
