Metadata-Version: 2.1
Name: btester
Version: 0.1.1
Summary: Python framework optimized for running backtests on multiple assetss
Home-page: https://github.com/pawelkn/btester
Author: Paweł Knioła
Author-email: Paweł Knioła <pawel.kn@gmail.com>
License: MIT License
Project-URL: Homepage, https://github.com/pawelkn/btester
Project-URL: Bug Tracker, https://github.com/pawelkn/btester/issues
Keywords: python,python3,quantitative,analysis,backtesting,portfolio,parallel,algorithmic,trading
Classifier: License :: OSI Approved :: MIT License
Classifier: Operating System :: OS Independent
Classifier: Programming Language :: Python :: 3.7
Classifier: Programming Language :: Python :: 3.8
Classifier: Programming Language :: Python :: 3.9
Classifier: Programming Language :: Python :: 3.10
Classifier: Programming Language :: Python :: 3.11
Classifier: Programming Language :: Python :: 3.12
Requires-Python: >=3.7
License-File: LICENSE
Requires-Dist: pandas >=0.22
